midi_ddsp/__init__.py
midi_ddsp/download_model_weights.py
midi_ddsp/hparams_synthesis_generator.py
midi_ddsp/midi_ddsp_synthesize.py
midi_ddsp/data_handling/__init__.py
midi_ddsp/data_handling/get_dataset.py
midi_ddsp/data_handling/instrument_name_utils.py
midi_ddsp/modules/__init__.py
midi_ddsp/modules/cond_rnn.py
midi_ddsp/modules/ddsp_inference.py
midi_ddsp/modules/discriminator.py
midi_ddsp/modules/expression_generator.py
midi_ddsp/modules/expression_generator_dataset.py
midi_ddsp/modules/gan_loss.py
midi_ddsp/modules/get_synthesis_generator.py
midi_ddsp/modules/interpretable_conditioning.py
midi_ddsp/modules/loss_helper.py
midi_ddsp/modules/midi_decoder.py
midi_ddsp/modules/model.py
midi_ddsp/modules/recon_loss.py
midi_ddsp/modules/reverb_modules.py
midi_ddsp/modules/synth_params_decoder.py
midi_ddsp/utils/__init__.py
midi_ddsp/utils/audio_io.py
midi_ddsp/utils/create_expression_generator_dataset_utils.py
midi_ddsp/utils/file_utils.py
midi_ddsp/utils/inference_utils.py
midi_ddsp/utils/midi_synthesis_utils.py
midi_ddsp/utils/summary_utils.py
midi_ddsp/utils/training_utils.py
midi_ddsp-0.2.6.dist-info/LICENSE
midi_ddsp-0.2.6.dist-info/METADATA
midi_ddsp-0.2.6.dist-info/WHEEL
midi_ddsp-0.2.6.dist-info/entry_points.txt
midi_ddsp-0.2.6.dist-info/top_level.txt
midi_ddsp-0.2.6.dist-info/RECORD
