Metadata-Version: 2.1
Name: midi-ddsp
Version: 0.2.6
Summary: Synthesis of MIDI with DDSP
Home-page: http://github.com/magenta/midi-ddsp
Author: Google Inc. & Yusong Wu
Author-email: no-reply@google.com, wuyusongwys@gmail.com
License: Apache 2.0
Keywords: audio MIDI MIDI-synthesizer machinelearning music
Classifier: Development Status :: 3 - Alpha
Classifier: Intended Audience :: Developers
Classifier: Intended Audience :: Science/Research
Classifier: License :: OSI Approved :: Apache Software License
Classifier: Topic :: Scientific/Engineering :: Artificial Intelligence
License-File: LICENSE
Requires-Dist: tensorflowjs (<3.19)
Requires-Dist: crepe (<0.0.13)
Requires-Dist: note-seq (<0.0.4)
Requires-Dist: ddsp (==3.2.0)
Requires-Dist: pretty-midi
Requires-Dist: music21
Requires-Dist: pandas
Requires-Dist: tensorflow-datasets
Provides-Extra: test
Requires-Dist: pytest ; extra == 'test'
Requires-Dist: pylint (!=2.5.0) ; extra == 'test'
